slowsilent/__init__.py
slowsilent/__main__.py
slowsilent/core/__init__.py
slowsilent/tests/__init__.py
slowsilent/tests/test_1984.py
slowsilent-0.0.4.dist-info/licenses/LICENSE.txt
slowsilent-0.0.4.dist-info/METADATA
slowsilent-0.0.4.dist-info/WHEEL
slowsilent-0.0.4.dist-info/top_level.txt
slowsilent-0.0.4.dist-info/RECORD
