Metadata-Version: 2.4
Name: slowsilent
Version: 0.0.4
Summary: This project extends the silent periods in a sound file.
Author-email: Johannes <johannes-programming@mailfence.com>
License: The MIT License (MIT)
Project-URL: Download, https://pypi.org/project/slowsilent/#files
Project-URL: Index, https://pypi.org/project/slowsilent/
Project-URL: Source, https://github.com/johannes-programming/slowsilent/
Project-URL: Website, https://slowsilent.johannes-programming.online/
Classifier: Development Status :: 2 - Pre-Alpha
Classifier: License :: OSI Approved :: MIT License
Classifier: Natural Language :: English
Classifier: Operating System :: OS Independent
Classifier: Programming Language :: Python
Classifier: Programming Language :: Python :: 3
Classifier: Programming Language :: Python :: 3 :: Only
Classifier: Typing :: Typed
Requires-Python: >=3.11
License-File: LICENSE.txt
Requires-Dist: pydub>=0.25.1
Dynamic: license-file
